{"type":"Topology","objects":{"map":{"type":"GeometryCollection","bbox":[-87.6858210929999,10.713481547000114,-82.55878658799992,15.030969950000156],"geometries":[{"type":"Polygon","properties":{"name":"Rivas","name_alt":null,"fips":"NU00"},"id":"NIC-24","arcs":[[0,1,2,3,4]]},{"type":"Polygon","properties":{"name":"Rio San Juan","name_alt":null,"fips":null},"id":"NIC-4800","arcs":[[5,6,-2,7]]},{"type":"MultiPolygon","properties":{"name":"Atlántico Sur","name_alt":"Región Autónoma del Atlántico Norte","fips":"NU18"},"id":"NIC-644","arcs":[[[8]],[[9]],[[10]],[[11,-6,12,13,14,15]]]},{"type":"Polygon","properties":{"name":"Carazo","name_alt":null,"fips":"NU02"},"id":"NIC-654","arcs":[[16,-4,17,18,19]]},{"type":"Polygon","properties":{"name":"Granada","name_alt":null,"fips":"NU06"},"id":"NIC-655","arcs":[[20,21,-5,-17,22,23]]},{"type":"Polygon","properties":{"name":"Jinotega","name_alt":null,"fips":"NU07"},"id":"NIC-656","arcs":[[24,25,26,27,28,29]]},{"type":"MultiPolygon","properties":{"name":"Atlántico Norte","name_alt":"Región Autónoma del Atlántico Norte","fips":"NU17"},"id":"NIC-657","arcs":[[[30]],[[31]],[[32]],[[33]],[[34]],[[35]],[[36]],[[37]],[[38]],[[39]],[[40]],[[41]],[[42]],[[43]],[[44]],[[45]],[[46]],[[47]],[[48]],[[49]],[[50]],[[51]],[[52]],[[53]],[[54]],[[55]],[[56]],[[57]],[[58]],[[59]],[[60]],[[61]],[[62]],[[63]],[[64]],[[65]],[[66]],[[67]],[[68]],[[69]],[[70]],[[71]],[[72]],[[73]],[[74]],[[75]],[[76]],[[77]],[[78]],[[79]],[[80]],[[81]],[[82]],[[83]],[[84]],[[85]],[[86]],[[87]],[[88]],[[89]],[[90]],[[91]],[[92]],[[93]],[[94]],[[95]],[[96]],[[97]],[[98]],[[99]],[[100]],[[101]],[[102]],[[103]],[[104]],[[105]],[[106]],[[107]],[[108]],[[109]],[[110]],[[111]],[[112]],[[113]],[[114]],[[115]],[[116]],[[117]],[[118]],[[119]],[[120]],[[121]],[[122]],[[123]],[[-16,124,-30,125]]]},{"type":"Polygon","properties":{"name":"León","name_alt":null,"fips":"NU08"},"id":"NIC-658","arcs":[[126,127,128,129,130]]},{"type":"Polygon","properties":{"name":"Managua","name_alt":null,"fips":"NU10"},"id":"NIC-659","arcs":[[131,-24,132,-19,133,-128,134]]},{"type":"Polygon","properties":{"name":"Masaya","name_alt":null,"fips":"NU11"},"id":"NIC-660","arcs":[[-23,-20,-133]]},{"type":"Polygon","properties":{"name":"Chinandega","name_alt":null,"fips":"NU03"},"id":"NIC-663","arcs":[[135,136,-130,137]]},{"type":"Polygon","properties":{"name":"Estelí","name_alt":"Estel¡","fips":"NU05"},"id":"NIC-664","arcs":[[-26,138,-131,-137,139]]},{"type":"Polygon","properties":{"name":"Madriz","name_alt":null,"fips":"NU09"},"id":"NIC-665","arcs":[[-27,-140,-136,140,141]]},{"type":"Polygon","properties":{"name":"Matagalpa","name_alt":null,"fips":"NU12"},"id":"NIC-666","arcs":[[-15,142,-135,-127,-139,-25,-125]]},{"type":"Polygon","properties":{"name":"Nueva Segovia","name_alt":null,"fips":"NU13"},"id":"NIC-667","arcs":[[-28,-142,143]]},{"type":"Polygon","properties":{"name":"Boaco","name_alt":null,"fips":"NU01"},"id":"NIC-668","arcs":[[144,-21,-132,-143,-14]]},{"type":"Polygon","properties":{"name":"Chontales","name_alt":null,"fips":"NU04"},"id":"NIC-669","arcs":[[-8,-1,-22,-145,-13]]}]}},"arcs":[[[42186,22398],[8219,-1136]],[[50405,21262],[-4671,-11218],[795,-850],[1748,-754],[953,-472],[2622,-1132],[1668,-660],[1109,-752]],[[54629,5424],[-458,-192],[-448,58],[-3149,1361],[-2801,1215],[-700,303],[-2634,1141],[-1974,856],[-631,415],[-550,581],[-559,337],[-650,-318],[-549,-866],[-357,-908],[-471,-898],[-13,8],[-973,475],[-379,69],[-274,175],[-154,412],[-184,835],[-355,619],[-2081,2731],[-172,144],[-92,50],[-298,247],[-64,98],[-678,224],[-302,331],[-655,930],[-520,314],[-666,825],[-850,566],[-282,296],[-76,188],[-166,622]],[[29464,18668],[1,3],[563,1209],[127,284],[61,89],[681,531]],[[30897,20784],[460,-142],[147,25],[69,82],[541,321],[73,59],[212,407],[304,762],[57,68],[55,39],[48,5],[33,-2],[99,-28],[84,-62],[76,-93],[193,-231],[92,-37],[865,260],[636,216],[7245,-35]],[[60042,26613],[395,-1595],[292,-627],[161,-157],[124,-151],[46,-147],[-22,-279],[25,-604],[211,-585],[194,-728],[-9,-186],[-34,-258],[-193,-529],[-275,-1114],[-55,-448],[-6,-301],[143,-895],[73,-895],[1296,-559],[564,-402],[1555,-1133],[302,-351],[115,-317],[14,-287],[39,-297],[147,-352],[175,-214],[181,-153],[918,-552],[769,-648],[554,-649],[169,-257],[398,-767],[99,-135],[80,-61],[59,4],[68,-19],[74,-41],[124,-86],[57,-23],[109,-35],[147,-64],[56,-11],[44,-4],[200,31],[125,2],[53,-6],[125,-34],[319,-151],[243,-95],[619,94],[126,-15],[63,-41],[-16,-129],[-2,-67],[9,-61],[26,-49],[214,-260],[191,-186],[104,-59],[79,-12],[167,104],[123,33],[44,18],[87,53],[39,34],[98,67],[72,32],[144,29],[119,-23],[187,-83],[90,-14],[73,3],[44,27],[50,22],[45,25],[42,32],[154,72],[187,29],[95,28],[272,151],[57,-12],[33,-43],[4,-72],[-31,-430],[3,-73],[25,-126],[22,-56],[57,-93],[66,-81],[29,-45],[21,-57],[9,-69],[3,-153],[14,-90],[31,-89],[84,-121],[68,-43],[56,-1],[47,23],[40,30],[47,27],[139,6],[220,-20],[769,-176],[145,-56],[44,-36],[68,-76],[355,-542],[283,-546],[505,-638],[337,-306]],[[77385,5338],[154,-493],[343,76],[-74,247],[284,48],[414,-99],[320,-196],[-139,16],[-124,-4],[-115,29],[-141,-118],[23,-118],[-9,-112],[18,-995],[179,-824],[-56,-629],[-685,-413],[-1281,-359],[-101,-28],[-1294,-575],[-399,-547],[-73,-52],[-533,125],[-131,-52],[-271,-221],[-191,-44],[-182,33],[-131,73],[-1177,1087],[-89,395],[-215,171],[-262,-51],[-232,-271],[-333,93],[-484,-364],[-236,271],[-134,0],[-224,-199],[-225,100],[-362,415],[-234,-46],[-170,29],[-139,23],[-304,8],[-218,-186],[-103,157],[-429,404],[-44,80],[-80,99],[-36,130],[86,179],[81,65],[271,166],[-73,555],[-337,332],[-372,223],[-174,227],[-207,164],[-907,408],[-206,225],[-54,163],[-260,382],[-85,167],[-41,287],[4,234],[-45,174],[-185,110],[-166,-116],[-1049,-801],[-185,-91],[-214,25],[-208,96],[-175,116],[-166,164],[-444,647],[-82,70],[-94,60],[-101,48],[-105,34],[-973,502],[-450,169],[-420,-28],[-341,57],[-742,625],[-346,178],[-610,-171],[-1444,-1115],[-2012,-1557]],[[50405,21262],[355,712],[48,67],[81,88],[303,176],[390,321],[179,114],[123,57],[90,-40],[49,-15],[95,13],[364,160],[118,80],[64,54],[65,129],[89,138],[136,170],[27,41],[19,52],[31,54],[81,106],[38,67],[19,94],[1,27],[54,150],[290,523],[834,213],[489,377],[1288,1384],[64,111],[94,33],[101,18],[1437,-21],[398,83],[85,1],[166,-55],[78,-7],[295,34],[66,-11],[73,-20],[94,-44],[219,-54],[747,-29]],[[77343,27104],[11,-310],[-125,193],[-148,629],[-44,834],[138,730],[402,323],[30,-5],[23,-19],[7,-45],[-10,-74],[-128,-238],[-135,-377],[-102,-422],[-33,-373],[114,-846]],[[90905,33855],[-564,-725],[-39,517],[185,406],[272,164],[222,-209],[-76,-153]],[[91770,36678],[-9,-255],[-97,121],[-146,80],[-54,94],[88,195],[88,57],[49,-173],[12,-86],[69,-33]],[[81065,53714],[427,-3007],[-657,-6110],[0,-1351],[65,-223],[283,-665],[189,-737],[544,-888],[130,-577],[-50,-708],[-204,-378],[-396,-152],[-627,-28],[-478,-114],[-488,-205],[-455,-84],[-389,245],[147,165],[402,332],[117,151],[17,271],[-74,364],[-125,319],[-428,445],[35,1515],[-91,579],[71,45],[24,3],[11,12],[40,84],[121,0],[690,-257],[481,723],[164,1043],[-258,705],[0,172],[169,220],[66,312],[32,1294],[35,49],[79,77],[91,117],[60,159],[-65,621],[-378,369],[-522,148],[-498,-46],[-403,-273],[-173,-428],[11,-471],[152,-409],[429,-268],[44,-47],[-2,-78],[33,-393],[29,-162],[83,-159],[90,-66],[75,-90],[30,-238],[-9,-392],[-43,-160],[-93,-175],[77,-109],[201,-366],[-611,-415],[-1038,-1014],[-627,-310],[-842,-104],[-355,-136],[-145,-306],[0,-1206],[23,-26],[78,51],[164,-12],[235,-58],[157,6],[131,-48],[156,-216],[133,-1035],[-77,-495],[-137,-468],[-65,-442],[146,-422],[362,-206],[611,153],[104,-357],[-23,-231],[-100,-454],[-22,-264],[40,-145],[91,211],[309,1189],[119,299],[172,122],[385,-65],[82,-176],[-911,-2130],[-433,-2748],[143,-2965],[148,-498],[-133,-94],[-146,-64],[80,476],[-138,396],[-487,707],[-205,588],[166,248],[284,228],[155,533],[-100,393],[-256,452],[-344,390],[-366,203],[-592,-73],[29,-344],[311,-214],[252,314],[146,0],[329,-400],[135,-242],[56,-307],[-71,-391],[-296,-503],[-32,-371],[-110,-442],[-350,-14],[-805,284],[-105,-77],[238,-170],[479,-227],[115,-181],[79,-248],[45,-286],[14,-306],[-40,-209],[-174,-427],[-39,-169],[32,-128],[67,-132],[44,-145],[-23,-155],[-102,-142],[-109,-68],[-102,-42],[-74,-65],[-361,-545],[-111,-88],[-168,-68],[-191,-167],[-163,-211],[-83,-200],[256,-201],[312,-332],[265,-358],[168,-445],[142,-122],[190,-80],[197,-28],[288,38],[21,104],[-81,152],[-28,179],[133,450],[107,236],[173,91],[325,13],[188,-190],[903,-4226],[47,-816],[-10,-298],[-25,-182],[-74,-142],[-156,-169],[-38,67],[-276,-66],[-270,-104],[-22,-56],[-154,-76],[-194,-335],[-177,-76],[-237,-5],[-190,-34],[-163,-91],[-156,-173],[-199,-718],[-189,-1084],[-263,-818],[-414,75],[-122,0],[-619,-923],[-178,-356],[-103,-397],[3,-2344],[597,-3038],[422,-1207],[585,-1056],[189,-578],[466,-871],[164,-184],[355,-257],[141,-445],[0,-1]],[[60042,26613],[-101,387],[-139,306],[-19,67],[-17,100],[155,159],[761,371],[-2493,1395],[-135,236],[-1236,3639],[-259,1381],[-28,765],[123,520],[-61,350],[-690,1429],[-115,145],[-141,138],[-133,169],[-144,280],[-101,377],[-82,748],[23,394],[55,285],[111,313],[26,135],[-40,157],[-123,243],[-260,295],[-407,718],[-426,1104],[-115,225],[-564,604],[-468,793]],[[52999,44841],[-103,119],[-224,134],[-21,77],[-10,103],[57,359],[-25,427],[-85,293],[-168,368],[-119,163],[-115,121],[-175,110],[-154,286],[-96,46],[-573,505],[-362,228],[-364,-10],[-373,-393],[-101,-276],[-69,-649],[-85,-341],[-57,8],[-162,-115],[-141,-141],[9,-68],[-65,-43],[-261,-288],[198,-374],[21,-344],[-157,-179],[-329,121]],[[48890,45088],[-504,1259],[-152,784],[-84,260],[-189,441],[-21,218],[33,227],[76,183],[131,152],[171,102],[287,27],[216,-36],[233,-7],[189,74],[222,231],[67,222],[-4,366],[67,112],[197,33],[166,-38],[346,-122],[214,-29],[235,10],[274,60],[532,185],[196,27],[1157,-234],[254,-94],[76,106],[240,183],[121,128],[199,351],[139,382],[394,-87],[442,353],[409,456],[287,227],[231,29],[366,117],[269,13],[250,-74],[117,-99],[102,-13],[209,186],[107,50],[84,-22],[55,22],[39,346],[83,231],[19,77],[23,334],[122,773],[83,195],[411,527],[12,13],[131,120],[73,56],[13,16],[-53,8],[-51,-5],[-55,-14],[-48,-23],[-217,-151],[-54,-16],[-59,-11],[-65,1],[-60,12],[-52,20],[-45,29],[-40,35],[-64,85],[-55,91],[-283,679],[-122,450],[-23,54],[-151,226],[-78,74],[-42,29],[-49,24],[-54,18],[-47,23],[-45,29],[-142,155],[-41,28],[-41,21],[61,157],[63,121],[840,1310]],[[57233,57956],[5042,713],[2720,14],[386,60],[243,101],[239,302],[205,157],[146,55],[126,8],[149,-17],[104,-31],[123,-70],[134,-102],[229,-76],[190,8],[1175,381],[264,39],[154,-46],[51,-115],[376,-1372],[79,-166],[110,-146],[126,-29],[167,-95],[471,165],[306,-70],[-60,103],[-106,232],[-101,125],[370,-80],[301,-133],[233,56],[162,488],[132,-106],[91,-11],[176,117],[133,0],[177,-126],[75,100],[-21,231],[-109,269],[204,-41],[79,-62],[296,-30],[1581,-73],[375,-68],[198,-96],[153,-107],[204,-98],[336,-108],[150,-88],[73,-106],[-13,-131],[-42,-133],[-71,-138],[-369,-525],[-70,-133],[-43,-132],[-13,-131],[17,-122],[57,-104],[84,-93],[1466,-1242],[1920,-1302],[358,-137],[796,43],[979,-72],[357,54],[2,0]],[[31467,26466],[-95,-246],[-399,-846],[-110,-581],[68,-570],[84,-392],[3,-271],[-46,-205],[-233,-376],[-181,-426],[-80,-716],[23,-335],[50,-209],[346,-509]],[[29464,18668],[-19,68],[-604,316],[-727,823],[-1796,921],[-304,261],[-260,355],[-219,730],[-2336,2084],[-116,170]],[[23083,24396],[1,2],[490,554],[194,139],[155,7],[118,19],[223,64],[107,47],[76,44],[243,273],[203,347],[527,459],[142,161],[378,720],[1220,1158],[232,412]],[[27392,28802],[212,-296],[1784,-840],[572,-315],[256,-414],[45,-57],[1037,-360],[169,-54]],[[35777,34401],[122,-446],[29,-351],[32,-176],[104,-149],[165,-139],[313,-143],[530,-537],[1046,-1705],[1459,119]],[[39577,30874],[2609,-8476]],[[31467,26466],[373,963],[186,478],[68,174],[700,1811],[788,2022],[-64,355],[-647,859]],[[32871,33128],[1639,858],[612,517],[162,70],[146,-3],[347,-169]],[[42508,61542],[-1086,-821],[-380,-170],[-457,-2],[-408,-321],[-273,-363],[-286,-534],[-342,-678],[-1422,-1937],[-732,-740],[-213,-146],[-903,-903],[-1106,-1213],[-426,-349],[-197,-77],[-247,-40],[-708,34],[-234,-43],[-98,-57],[-255,-364],[-669,595],[-301,356],[-283,194],[-176,88],[-268,-8],[-98,5]],[[30940,54048],[-306,432],[-855,587],[-1471,1704],[-136,244],[-126,325],[229,440],[59,385],[-50,289],[282,963],[-179,993],[7,494],[54,389],[113,357],[166,350]],[[28727,62000],[717,890],[316,322],[311,66],[274,13],[241,-118],[186,248],[758,701],[187,262]],[[31717,64384],[188,266],[218,101],[206,-297],[191,102],[1019,102],[337,-27],[217,-146],[165,-175],[181,-114],[261,39],[137,116],[329,541],[436,374],[356,205],[213,305],[-33,1378],[61,576],[178,534],[564,1121],[84,282],[58,306],[29,1096],[118,377],[193,266],[468,331]],[[37891,72043],[13,-6],[42,45],[135,142],[161,374],[41,359],[-111,269],[-292,105],[-73,202],[81,446],[193,697],[23,507],[95,127],[202,-54],[346,-27],[248,135],[396,397],[167,-58],[120,0],[-9,109],[30,27],[54,-1],[59,23],[-63,243],[684,242],[190,227],[184,322],[427,164],[167,34],[322,67],[365,139],[182,317],[43,370],[112,307],[702,222],[332,224],[505,458],[226,325],[215,447],[161,440],[142,593],[187,363],[224,339],[188,209],[85,18],[209,-38],[82,20],[55,76],[55,169],[138,193],[79,156],[107,129],[183,54],[464,266],[202,51],[739,0],[482,98],[488,187],[401,281],[227,382],[-20,528],[-250,462],[-349,367],[-314,239],[534,474],[22,147],[-46,354],[24,147],[450,553],[70,150],[39,1170],[85,643],[154,330],[356,-105],[311,-396],[331,-285],[412,225],[695,803],[117,315]],[[51924,90076],[93,-12],[143,-40],[55,-34],[62,-56],[46,-85],[41,-97],[31,-145],[5,-154],[-102,-333],[-29,-137],[3,-137],[-7,-106],[-37,-237],[-10,-138],[5,-200],[-13,-216],[17,-68],[31,-55],[261,-239],[290,-182],[87,-94],[70,-143],[31,-182],[-35,-225],[-218,-434],[-27,-147],[19,-505],[-22,-116],[-151,-315],[-38,-152],[8,-155],[56,-167],[365,-552],[327,-353],[281,-391],[100,-75],[139,-42],[1743,-131],[50,-322],[-32,-560],[-426,-2651],[-61,-1077],[180,-844],[-39,-273],[-179,-446],[-1186,-2306],[-2475,-4589],[-99,-117],[-88,-46],[-1864,996],[-73,-25],[-2378,-1717],[-41,-13],[-1569,-252],[-98,-125],[-93,-210],[-173,-556],[-152,-279],[-140,-187],[-203,-153],[-34,-142],[17,-208],[157,-393],[131,-259],[94,-309],[31,-222],[-205,-718],[-9,-419],[8,-114],[-24,-215],[-67,-182],[-214,-207],[-1059,-792],[-607,-625],[-111,-305],[-5,-822]],[[96304,79326],[-48,-25],[38,49],[10,-24]],[[95757,79478],[2,-16],[8,5],[7,-42],[-25,-14],[-8,13],[-1,-1],[-21,35],[38,20]],[[96002,79532],[-1,-42],[-27,12],[28,30]],[[95345,79748],[0,-28],[-57,20],[33,43],[24,-35]],[[96440,79812],[-13,-34],[-53,27],[2,48],[64,-41]],[[96421,79937],[-7,-44],[-56,16],[63,28]],[[95210,79969],[2,-17],[9,5],[5,-41],[-24,-14],[-8,13],[-2,-1],[-21,34],[39,21]],[[95211,80050],[0,-28],[-24,32],[24,-4]],[[95137,80084],[3,-17],[8,5],[6,-41],[-25,-14],[-8,13],[-2,-1],[-20,34],[38,21]],[[94848,80319],[-13,-22],[-21,56],[34,-34]],[[94871,80474],[1,-17],[9,5],[5,-41],[-24,-14],[-8,13],[-2,-1],[-20,34],[39,21]],[[99999,81600],[-74,-76],[-20,107],[94,-31]],[[91443,81745],[-33,-6],[6,38],[27,-32]],[[91416,81967],[5,-84],[-37,9],[32,75]],[[92417,82121],[0,-21],[-47,21],[47,0]],[[92551,82214],[-33,-3],[30,67],[3,-64]],[[93092,82563],[-67,0],[41,88],[26,-88]],[[91943,82682],[1,-17],[8,5],[7,-41],[-25,-14],[-8,13],[-2,0],[-20,34],[39,20]],[[99937,82692],[-30,0],[13,40],[17,-40]],[[99810,82735],[-18,0],[0,22],[18,21],[18,-21],[-18,-22]],[[93996,82779],[-24,-1],[22,36],[2,-35]],[[91847,82821],[-19,0],[-18,29],[28,9],[9,-38]],[[93962,82850],[-3,-29],[-24,12],[1,31],[26,-14]],[[94178,82900],[-48,-22],[-9,20],[57,2]],[[92489,83108],[-11,-57],[-29,28],[40,29]],[[92380,83070],[-47,-19],[9,77],[38,-58]],[[92502,83158],[0,-21],[-47,21],[47,0]],[[92380,83262],[-11,-25],[-28,13],[22,45],[17,-33]],[[92329,83365],[-8,-40],[-37,1],[0,22],[45,17]],[[90388,83403],[3,-17],[7,5],[7,-41],[-25,-15],[-8,13],[-2,0],[-20,34],[38,21]],[[90713,83486],[-45,-73],[-18,21],[63,52]],[[90533,83532],[2,-17],[9,5],[5,-41],[-24,-14],[-8,14],[-2,-2],[-20,35],[38,20]],[[90390,83551],[-25,-53],[-19,25],[44,28]],[[90614,83492],[-18,-8],[-45,53],[60,15],[3,-60]],[[91992,83498],[-30,0],[68,58],[-38,-58]],[[90468,83498],[-19,0],[-6,87],[25,-87]],[[90698,83545],[-17,0],[-19,28],[32,25],[4,-53]],[[90790,83594],[-12,-49],[-42,14],[12,64],[42,-29]],[[90625,83613],[-29,-12],[-6,22],[24,65],[11,-75]],[[99403,83711],[-194,-342],[-54,168],[102,151],[146,23]],[[90208,83695],[-37,-7],[9,62],[28,-55]],[[90135,83711],[-38,-23],[-14,35],[8,44],[54,46],[13,-46],[-23,-56]],[[99125,83932],[59,-230],[-181,57],[122,173]],[[91129,83962],[-24,-1],[9,33],[15,-32]],[[91221,83971],[-31,-10],[-5,52],[36,-42]],[[91134,84069],[-53,-22],[1,53],[52,-31]],[[90662,85035],[-30,-21],[7,74],[23,-53]],[[93378,85165],[-37,-36],[-8,102],[45,-66]],[[93473,85292],[2,-17],[8,5],[6,-41],[-24,-15],[-8,13],[-2,-1],[-20,35],[38,21]],[[93388,85346],[-35,-45],[-12,81],[47,-36]],[[90437,85677],[-30,0],[9,43],[21,-43]],[[90376,85797],[2,-17],[8,5],[6,-41],[-24,-15],[-8,13],[-2,-1],[-20,35],[38,21]],[[96610,84680],[-357,-187],[-1036,103],[-84,10],[76,0],[13,-1],[41,12],[23,57],[-8,91],[313,203],[128,260],[70,265],[143,219],[317,183],[259,-2],[171,-189],[65,-379],[-134,-645]],[[94082,85852],[-207,-89],[0,268],[207,-179]],[[90851,86083],[-24,-1],[8,33],[16,-32]],[[97083,86328],[-24,-32],[-9,49],[33,-17]],[[96854,86330],[-26,-4],[0,35],[32,17],[-6,-48]],[[97424,86458],[-25,-3],[-5,14],[17,29],[13,-40]],[[97178,86560],[-23,-34],[-31,38],[54,-4]],[[97411,86573],[-24,0],[24,28],[0,-28]],[[97382,86618],[-8,-45],[-23,31],[31,14]],[[97040,86637],[-5,-22],[-13,29],[18,-7]],[[97119,86677],[2,-17],[7,6],[7,-42],[-25,-14],[-8,13],[-1,0],[-21,34],[39,20]],[[93814,86654],[-24,-10],[-22,46],[57,-13],[-11,-23]],[[96981,86680],[-19,-22],[-22,17],[4,63],[42,-8],[-5,-50]],[[93766,86752],[0,-50],[-41,50],[41,0]],[[93545,86880],[3,-17],[8,5],[6,-41],[-25,-14],[-8,13],[-2,-2],[-20,35],[38,21]],[[94026,86972],[-54,-39],[-10,25],[64,14]],[[93303,86958],[-47,-40],[-9,73],[56,-33]],[[93632,87073],[-48,-25],[-6,14],[16,30],[38,-19]],[[94848,87336],[-13,0],[-14,57],[51,-7],[-24,-50]],[[94785,87412],[1,-17],[9,5],[5,-40],[-23,-15],[-9,14],[-1,-1],[-21,34],[39,20]],[[94652,87513],[2,-17],[8,5],[6,-41],[-24,-14],[-8,13],[-3,-1],[-20,34],[39,21]],[[94908,87479],[-25,0],[10,53],[15,-53]],[[94829,87544],[-20,-21],[-23,71],[43,-50]],[[90983,87772],[2,-16],[8,5],[5,-41],[-23,-15],[-8,14],[-3,-1],[-20,35],[39,19]],[[99570,88899],[-45,-3],[19,54],[8,6],[18,-57]],[[92125,88958],[2,-17],[8,5],[6,-41],[-24,-14],[-9,12],[-2,-1],[-19,35],[38,21]],[[99536,89015],[2,-17],[8,5],[5,-37],[-10,-10],[-13,-8],[-8,14],[-2,-2],[-21,35],[39,20]],[[99659,88988],[-13,-21],[-49,63],[62,-42]],[[99789,88984],[-58,-17],[-5,78],[63,-61]],[[98152,89140],[110,-448],[-73,72],[-115,192],[78,184]],[[96608,89173],[1,-17],[8,5],[7,-41],[-24,-14],[-9,13],[-1,-1],[-21,35],[39,20]],[[99948,89274],[3,-17],[8,4],[5,-40],[-24,-14],[-8,13],[-2,-2],[-20,35],[38,21]],[[92076,89317],[3,-17],[8,5],[6,-41],[-25,-14],[-8,13],[-1,-2],[-21,35],[38,21]],[[99620,89317],[3,-17],[8,5],[5,-41],[-23,-14],[-8,13],[-2,-2],[-21,35],[38,21]],[[99911,89332],[-34,-6],[-2,71],[36,-65]],[[97403,89694],[-22,-49],[-30,1],[4,47],[48,1]],[[97891,90006],[-18,0],[5,52],[31,-9],[-18,-43]],[[95806,90598],[13,-275],[-133,151],[120,124]],[[98468,90631],[2,-17],[8,4],[6,-40],[-25,-14],[-8,13],[-2,-1],[-20,35],[39,20]],[[97847,90933],[3,-16],[8,5],[6,-41],[-24,-15],[-8,14],[-2,-1],[-21,34],[38,20]],[[97806,91109],[-19,-22],[-97,75],[70,16],[46,-69]],[[97387,94809],[0,-43],[-40,27],[21,59],[19,-43]],[[57233,57956],[-357,624],[-1948,2870],[-115,235],[-67,84],[-81,27],[-1769,-1917],[-176,-83],[-301,-34],[-1294,33],[-651,-69],[-495,-340],[-253,-418],[-159,-417],[-230,-804],[-242,-585],[-169,-226],[-190,-169],[-559,-302],[-509,-143],[-207,32],[-601,293],[-139,228],[-232,34],[-37,45],[-24,207],[-38,76],[-68,54],[-274,158],[-147,118],[-79,27],[-65,1],[-107,-35],[-119,-17],[-60,4],[-58,9],[-48,24],[-44,33],[-559,599],[-108,98],[-92,61],[-263,123],[-388,441],[-993,1553],[-410,1054]],[[51924,90076],[28,76],[-506,-1],[115,178],[430,469],[-552,454],[-106,226],[307,96],[100,54],[64,139],[102,857],[174,362],[266,289],[40,31],[304,237],[349,287],[894,998],[320,215],[1166,244],[514,26],[506,-176],[429,-368],[286,-549],[-60,-65],[-153,-227],[-10,-45],[388,-56],[54,-280],[-20,-308],[399,-312],[203,-387],[294,-793],[361,250],[373,-47],[756,-376],[439,-109],[1424,-49],[-74,-164],[-58,-454],[296,106],[206,-131],[204,-202],[299,-103],[216,73],[505,326],[727,295],[359,511],[271,584],[257,438],[190,-223],[140,-602],[149,-123],[297,-32],[474,-123],[216,-18],[400,244],[100,509],[-101,1087],[108,275],[245,20],[270,-108],[176,-115],[150,-147],[462,-572],[236,-113],[287,26],[475,160],[116,78],[79,111],[99,96],[178,45],[164,-33],[92,-55],[82,-11],[134,99],[0,173],[-171,192],[-135,212],[-226,544],[213,206],[143,12],[447,-328],[50,-107],[73,-82],[206,-31],[329,12],[100,-63],[37,-179],[335,-47],[1929,119],[-101,190],[4,214],[97,530],[235,-153],[314,-388],[249,-77],[-24,98],[-96,218],[141,-67],[77,-26],[68,-57],[113,-166],[237,247],[348,224],[387,143],[359,4],[-151,118],[-97,113],[-139,272],[1088,76],[405,183],[-40,359],[247,18],[201,-32],[144,-105],[74,-197],[145,0],[-185,665],[75,257],[364,200],[387,61],[433,-26],[358,-123],[166,-243],[145,0],[85,283],[41,312],[96,251],[477,206],[486,447],[281,96],[-38,82],[-53,164],[-43,70],[290,-97],[109,-61],[-59,310],[25,270],[109,99],[192,-205],[11,352],[32,142],[103,154],[-132,224],[66,117],[197,26],[256,-51],[104,-114],[237,-420],[179,-114],[458,63],[395,272],[304,386],[187,402],[243,-225],[251,-114],[203,-145],[102,-307],[294,223],[336,26],[859,-105],[-232,-131],[-15,-122],[143,-116],[237,-107],[81,16],[864,-16],[515,273],[271,59],[659,-44],[257,48],[-143,-238],[-357,-191],[-177,-218],[-286,392],[-235,-271],[-187,-491],[-145,-263],[-249,-140],[-238,-332],[-176,-393],[-69,-320],[-52,-108],[-248,-281],[-100,-165],[-50,-225],[-36,-496],[-48,-228],[-159,-289],[-235,-207],[-672,-308],[48,139],[54,110],[165,225],[0,-173],[66,129],[38,106],[17,114],[1,154],[-151,-107],[-63,-18],[-175,125],[0,143],[234,127],[222,33],[195,-83],[149,-220],[-15,437],[-209,600],[-53,466],[-121,464],[-279,76],[-316,-136],[-230,-166],[-384,-413],[-864,-1281],[-205,-550],[191,231],[65,100],[267,-246],[212,-951],[131,-212],[257,-179],[281,-312],[296,-111],[299,429],[-142,142],[-360,255],[-164,78],[220,141],[225,-76],[205,-228],[160,-312],[-13,529],[142,164],[174,-201],[763,-4057],[42,-130],[183,-433],[161,-1105],[946,-3175],[102,-910],[-94,-792],[-530,-1462],[-1620,-3020],[-699,-982],[-100,-383],[-138,-283],[-928,-752],[-392,-642],[-271,-738],[-469,-2150],[-751,-2922],[-462,-2642],[29,-1135],[-81,-554],[-4,-442],[-409,-1153],[-347,-1530],[-215,-2982],[38,-557],[138,-321],[-146,-145],[110,-284],[652,-4587]],[[27733,49450],[-57,-574],[-231,-2296],[-197,-2041]],[[27248,44539],[-771,-552],[-278,-310],[-164,-258],[-53,-133],[-23,-116],[5,-82],[-33,-238],[0,-85],[10,-66],[-6,-107],[-25,-146],[-118,-407],[-19,-109],[10,-65],[34,-118],[22,-55],[187,-311],[5,-7],[115,-119],[24,-43],[15,-58],[3,-148],[11,-75],[23,-87],[-28,-72],[-78,-109],[-1898,-2183],[-1302,-1529],[-272,-443],[-31,-360],[-2,-1643],[25,-156],[53,-136],[82,-79],[97,-67],[126,-173],[27,-416],[-248,-644],[-380,-512],[-736,-654],[-110,-64],[-58,-2],[-276,68],[-278,122],[-35,7],[-51,2],[-54,-7],[-53,-16],[-292,-122],[-138,-35],[-71,-38],[-53,-41],[-28,-46],[-19,-57],[-2,-67],[8,-66],[31,-126],[135,-320],[93,-129],[24,-50],[18,-82],[-1,-55],[-10,-61],[-84,-173],[-69,-92],[-483,-406],[-2,-2]],[[19799,29810],[-373,545],[-736,1487],[-685,2177],[-193,351],[-486,489],[-3993,2845],[-250,358],[-1099,738],[-596,748],[-1347,706],[-50,534],[224,-345],[382,-296],[446,-212],[426,-96],[-450,575]],[[11019,40414],[2,2],[431,298],[961,124],[335,174],[330,225],[185,133],[1012,1222],[393,740],[150,457],[77,151],[378,420],[497,623],[477,602],[380,202],[376,525],[270,610],[140,159],[215,137],[1406,213],[277,83],[154,70],[348,251],[242,653],[58,724],[-181,2801],[-241,646],[-265,499],[-412,1106],[-190,785]],[[18824,55049],[338,157],[187,19],[258,-6],[310,-122],[379,-215],[230,20],[398,102],[1286,502],[1091,268],[236,-76],[148,-87],[353,-413],[513,-989],[198,-314],[101,-199],[137,-577],[-41,-727],[-430,-885],[-26,-268],[5,-196],[195,-406],[655,-381],[2388,-806]],[[33422,41890],[-119,-406],[78,-781],[92,-329],[133,-264],[247,-386],[491,-624],[69,-128],[23,-143],[-40,-455],[-4,-386],[33,-167],[62,-122],[1705,-1876],[42,-78],[-34,-134],[-322,-572],[-101,-638]],[[32871,33128],[-348,105],[-106,68],[-35,15],[-62,9],[-332,-54],[-668,-316],[-566,-117],[-353,-308],[-1185,-1365],[63,-295],[283,-338],[105,-173],[53,-137],[-26,-516],[-217,-413],[-110,-152],[-121,-131],[-155,-98],[-183,-59],[-154,-17],[-231,73],[-136,73],[-534,480],[-461,-660]],[[23083,24396],[-259,378],[-522,1372],[-211,208],[-196,123],[-515,607],[-304,506],[-331,728],[-64,345],[-95,322],[-225,268],[-480,436],[-82,121]],[[27248,44539],[3314,-853],[346,-128],[291,-312],[298,-391],[213,-202],[189,-149],[1206,-541],[317,-73]],[[18590,59177],[22,-39],[369,-89],[113,-102],[58,-194],[23,-174],[-10,-140],[-30,-124],[-22,-57],[-177,-659]],[[18936,57599],[-205,-213],[-18,-27],[-50,-211],[-64,-723],[225,-1376]],[[11019,40414],[-35,46],[-250,235],[-270,93],[-167,151],[-439,971],[-122,0],[199,-858],[-318,324],[-509,749],[-375,417],[-242,118],[-1219,1099],[-162,196],[-88,240],[-106,402],[-54,-125],[-152,-220],[-59,-114],[-2146,2887],[-252,606],[83,-111],[81,-64],[235,-142],[0,145],[-93,38],[-173,134],[0,144],[-50,235],[-327,317],[-442,277],[-391,120],[0,-144],[518,-396],[271,-293],[10,-260],[-199,33],[-288,255],[-433,489],[-2288,1595],[-477,489],[-287,574],[-3,679],[367,803],[550,561],[562,408],[414,515],[96,888],[121,0],[-54,-498],[-67,-135],[219,0],[264,-41],[223,-79],[94,-110],[92,-67],[495,-493],[124,-82],[353,-551],[86,-76],[250,-175],[64,-65],[17,-151],[-41,-350],[24,-147],[638,-739],[830,-208],[2007,143],[0,173],[-1015,-30],[-510,65],[-219,209],[197,370],[943,548],[127,101],[4474,333],[289,-36],[449,-321],[230,-17],[106,377],[406,232],[499,365],[222,279],[457,829],[111,101],[287,167],[99,119],[52,227],[-77,83],[-109,57],[-50,146],[168,1218],[-35,58],[-147,372],[-36,135],[33,62],[141,652],[139,311],[157,227],[938,935],[258,206],[313,104],[336,-33],[1123,-642],[182,-67],[185,56],[139,110]],[[30940,54048],[-736,-1165],[-126,-596],[-47,-126],[-87,-124],[-162,-133],[-248,-100],[-499,-127],[-230,-94],[-433,-286],[-151,-169],[-69,-95],[-310,-750],[-109,-833]],[[18936,57599],[1638,1914],[365,599],[163,407],[802,1630],[779,780],[518,92],[205,-74],[284,-162],[835,-460],[825,161],[1497,559],[1085,61],[366,-137],[79,-150],[193,-509],[157,-310]],[[18590,59177],[141,112],[267,287],[151,304],[42,356],[-115,663],[-42,141],[-141,295],[-126,132],[-133,36],[-116,71],[-74,231],[30,331],[248,639],[32,361],[-630,2779],[-10,394],[121,742],[-13,370],[-75,150],[-170,150]],[[17977,67721],[163,140],[149,236],[60,75],[90,77],[431,-7],[1366,-292],[386,-666],[85,-197],[173,-218],[214,-177],[329,-143],[223,-154],[244,-246],[306,174],[196,220],[440,133],[194,26],[1401,-26],[1088,-407],[626,9],[810,119],[228,-35],[303,-104],[378,-271],[595,-305],[177,256],[116,655],[62,151],[55,104],[429,197],[380,147],[674,-638],[158,-184],[190,-273],[432,-891],[589,-822]],[[48890,45088],[15,-250],[-21,-222],[-51,-187],[-76,-146],[-133,0],[-95,100],[-182,143],[-177,79],[-79,-85],[-56,-227],[-126,39],[-610,794],[-220,40],[-332,-251],[-133,0],[106,584],[27,63],[-140,126],[-311,22],[-369,232],[-644,258],[-134,81],[-68,224],[-163,229],[-197,180],[-171,71],[-115,27],[-149,-128],[-29,-46],[-32,-93],[-43,-104],[-62,-92],[-37,-39],[-85,-63],[-90,-49],[-152,-54],[-50,-29],[-33,-41],[-21,-55],[-109,-42],[-199,-24],[-1248,77],[-63,-14],[-52,-25],[-37,-38],[-31,-44],[-253,-590],[-59,-97],[-76,-35],[-115,-19],[-377,-3],[-90,-18],[-176,-108],[-397,-88],[-232,-50],[-238,-231],[-78,-43],[-56,2],[-114,72],[-310,68],[-256,81],[-3392,-823],[-316,-187],[-343,-837],[-933,-605],[-104,-94],[-576,-614]],[[17977,67721],[-80,69],[-76,120],[-38,210],[57,1235],[18,401],[45,323],[34,141],[92,95],[225,180],[443,258],[408,41],[850,-124],[1591,352],[770,52],[646,-411],[346,-113],[283,105],[262,160],[285,47],[308,-367],[116,-96],[184,-69],[136,-22],[1007,74],[358,102],[291,165],[227,297],[113,350],[153,686],[308,565],[1278,1590],[674,1216],[204,157],[230,103],[236,143],[228,276],[140,295],[76,223],[102,200],[219,230],[268,161],[1493,257],[-5,-257],[-211,-498],[56,-614],[1377,-1157],[423,-646],[131,-142],[271,-107],[179,44],[178,85],[266,19],[428,-218],[229,-402],[190,-475],[311,-438],[432,-173],[456,17],[397,-38],[259,-338],[37,-17]],[[52999,44841],[-248,-580],[-742,-1269],[-77,-184],[-48,-187],[-28,-259],[-10,-853],[-55,-257],[-102,-263],[-324,-478],[-215,-248],[-286,-254],[-573,-330],[-280,-52],[-118,-6],[-199,29],[-208,-56],[-294,-137],[-1142,-916],[-232,-149],[-798,-316],[-1053,-139],[-1400,-290],[-836,42],[-568,11],[-483,92],[-214,8],[-278,-97],[-736,-421],[-503,-428],[-93,-106],[-156,-248],[-39,-113],[-23,-149],[3,-563],[47,-421],[-4,-154],[-42,-161],[-391,-1046],[-23,-38],[-23,-45],[-27,-43],[-183,-343],[-94,-222],[-324,-2328]]],"transform":{"scale":[0.00005127085775857742,0.000043175315783158255],"translate":[-87.6858210929999,10.713481547000114]}}